sente.cpython-311-x86_64-linux-musl.so
sente-0.4.3.dist-info/LICENSE.txt
sente-0.4.3.dist-info/top_level.txt
sente-0.4.3.dist-info/WHEEL
sente-0.4.3.dist-info/RECORD
sente-0.4.3.dist-info/METADATA
sente.libs/libstdc++-a9383cce.so.6.0.28
sente.libs/libgcc_s-a04fdf82.so.1
