Metadata-Version: 2.1
Name: sente
Version: 0.4.3
Summary: Sente: a Python 3 native library for the game of Go.
Home-page: https://github.com/atw1020/sente
Author: Arthur Wesley
Author-email: arthur@electricfish.com
License: MIT
Classifier: Programming Language :: Python
Classifier: Programming Language :: Python :: 3
Classifier: Programming Language :: Python :: 3.8
Classifier: Programming Language :: Python :: 3.9
Classifier: Programming Language :: Python :: 3.10
Classifier: Operating System :: MacOS :: MacOS X
Classifier: Operating System :: POSIX :: Linux
Classifier: Operating System :: Microsoft :: Windows :: Windows 10
Requires-Python: >=3.8.*
License-File: LICENSE.txt
